certbot_dns_inwx/__init__.py
certbot_dns_inwx/_internal/__init__.py
certbot_dns_inwx/_internal/dns_inwx.py
certbot_dns_inwx/_internal/tests/__init__.py
certbot_dns_inwx/_internal/tests/dns_inwx_test.py
certbot_dns_inwx-3.0.3.dist-info/licenses/LICENSE
certbot_dns_inwx-3.0.3.dist-info/METADATA
certbot_dns_inwx-3.0.3.dist-info/WHEEL
certbot_dns_inwx-3.0.3.dist-info/entry_points.txt
certbot_dns_inwx-3.0.3.dist-info/top_level.txt
certbot_dns_inwx-3.0.3.dist-info/RECORD
