Metadata-Version: 2.4
Name: certbot-dns-inwx
Version: 3.0.3
Summary: INWX DNS Authenticator plugin for Certbot
Home-page: https://github.com/oGGy990/certbot-dns-inwx
Author: Oliver Ney
Author-email: oliver@dryder.de
License: Apache License 2.0
Classifier: Programming Language :: Python :: 3
Classifier: License :: OSI Approved :: Apache Software License
Classifier: Intended Audience :: System Administrators
Classifier: Topic :: Internet :: Name Service (DNS)
Classifier: Topic :: Security :: Cryptography
Classifier: Topic :: System :: Installation/Setup
Classifier: Topic :: System :: Networking
Classifier: Topic :: System :: Systems Administration
Classifier: Development Status :: 5 - Production/Stable
Classifier: Environment :: Plugins
Classifier: Operating System :: OS Independent
Requires-Python: >=3.8
License-File: LICENSE
Requires-Dist: setuptools>=41.6.0
Requires-Dist: inwx-domrobot>=3.2.0
Requires-Dist: acme>=3.0.0
Requires-Dist: certbot>=3.0.0
Provides-Extra: cname
Requires-Dist: dnspython; extra == "cname"
Provides-Extra: idna
Requires-Dist: idna; extra == "idna"
Provides-Extra: test
Requires-Dist: pytest; extra == "test"
Dynamic: author
Dynamic: author-email
Dynamic: classifier
Dynamic: description
Dynamic: description-content-type
Dynamic: home-page
Dynamic: license
Dynamic: license-file
Dynamic: provides-extra
Dynamic: requires-dist
Dynamic: requires-python
Dynamic: summary
